E2/p2.v
//Univseridad del Valle de Guatemala
//Gerardo Fuentes
//19389


//Modulo bus driver triestado 4 bits
module bdri4b(input E0, input[3:0]D, output [3:0]Q);

  assign Q = E == 1 ? D:4'bz;

endmodule

//Modulo accumulator
module Acc4b(input clk1, reset1, E1, input[3:0]oalu, output reg[3:0]oaccu);

  always@(posedge clk1, posedge reset1, E)
    if (reset1)  oaccu<=8'b0;
    else if (E)  oaccu<=oalu;

endmodule

//Modulo ALU
module ALU4b(input[3:0]inpta, inptb, input[2:0]seg,
             output reg carry, zero, output reg[4:0]oupt);

  always@(inpta, inptb, seg)
    case(seg)
      3'b000: {carry,oupt} <= inpta;
      3'b001: {carry,oupt} <= inpta - inptb;
      3'b010: {carry,oupt} <= inptb;
      3'b011: {carry,oupt} <= inpta + inptb;
      3'b100: {carry,oupt} <= ~(inpta & inptb);
    default oupt = inpta;
   endcase

   always@(oupt)
     if(oupt == 4'b0000) zero <= 1;

endmodule


//Modulo parte2 procesador
module part2(input reset, clk, ea, eb, ec, input[2:0]slct, input[3:0] d0,
             output crry, zro, output[3:0]outalu, outaccu, q0, q1);

  bdri4b bff1(ea, d0, q0);
  bdri4b bff2(eb, outalu, q1);
  ALU4b  alu4(outaccu, q0, slct, crry, zro, outalu);
  Acc4b  accu(clk, reset, ec, outalu, outaccu);


endmodule

E2/p2_tb.v
//Universidad del Valle de Guatemala
//Gerardo Fuentes
//19389

module testbench();

  reg RST, CLK, EA, EB, EC;
  reg[2:0] SLCT;
  reg[3:0] D0;
  wire CRRY, ZRO;
  wire[3:0] OUTALU, OUTACCU, Q0, Q1;

  part2  p2(RST, CLK, EA, EB, EC, SLCT, D0, CRRY, ZRO, OUTALU, OUTACCU, Q0, Q1);

  initial begin
     CLK = 0;
     forever #1 CLK = ~CLK;
  end

  initial begin
    RST = 1;
    #1 RST = 0;
  end

  initial begin
    #1  VAL = 12'b000000000000; Ea=1; Eb=1; load=0;
    #20 VAL = 12'b000000001010; Ea=1; Eb=1; load=1;
    #1  VAL = 12'b000000001010; Ea=1; Eb=1; load=1;
    #1  VAL = 12'b000000001010; Ea=1; Eb=1; load=0;


  end


  initial
    #100 $finish;

  initial begin
    $dumpfile("p2_tb.vcd");
    $dumpvars(0, testbench);
  end

endmodule

E2/p2_tb.vcd
$date
	Sat Nov 07 23:44:55 2020
$end
$version
	Icarus Verilog
$end
$timescale
	1ps
$end
$scope module testbench $end
$var wire 1 ! ZRO $end
$var wire 4 " Q1 [3:0] $end
$var wire 4 # Q0 [3:0] $end
$var wire 4 $ OUTALU [3:0] $end
$var wire 4 % OUTACCU [3:0] $end
$var wire 1 & CRRY $end
$var reg 1 ' CLK $end
$var reg 4 ( D0 [3:0] $end
$var reg 1 ) EA $end
$var reg 1 * EB $end
$var reg 1 + EC $end
$var reg 1 , RST $end
$var reg 3 - SLCT [2:0] $end
$scope module p2 $end
$var wire 1 ' clk $end
$var wire 4 . d0 [3:0] $end
$var wire 1 ) ea $end
$var wire 1 * eb $end
$var wire 1 + ec $end
$var wire 1 , reset $end
$var wire 3 / slct [2:0] $end
$var wire 1 ! zro $end
$var wire 4 0 q1 [3:0] $end
$var wire 4 1 q0 [3:0] $end
$var wire 4 2 outalu [3:0] $end
$var wire 4 3 outaccu [3:0] $end
$var wire 1 & crry $end
$scope module accu $end
$var wire 1 + E1 $end
$var wire 1 ' clk1 $end
$var wire 4 4 oalu [3:0] $end
$var wire 1 , reset1 $end
$var reg 4 5 oaccu [3:0] $end
$upscope $end
$scope module alu4 $end
$var wire 4 6 inpta [3:0] $end
$var wire 3 7 seg [2:0] $end
$var wire 4 8 inptb [3:0] $end
$var reg 1 & carry $end
$var reg 5 9 oupt [4:0] $end
$var reg 1 ! zero $end
$upscope $end
$scope module bff1 $end
$var wire 4 : D [3:0] $end
$var wire 1 ) E0 $end
$var wire 4 ; Q [3:0] $end
$upscope $end
$scope module bff2 $end
$var wire 4 < D [3:0] $end
$var wire 1 * E0 $end
$var wire 4 = Q [3:0] $end
$upscope $end
$upscope $end
$upscope $end
$enddefinitions $end
#0
$dumpvars
bx =
b0 <
bx ;
bx :
b0 9
bx 8
bx 7
b0 6
b0 5
b0 4
b0 3
b0 2
bx 1
bx 0
bx /
bx .
bx -
1,
x+
x*
x)
bx (
0'
x&
b0 %
b0 $
bx #
bx "
1!
$end
#1
0&
b0 "
b0 0
b0 =
b1 #
b1 1
b1 8
b1 ;
b0 -
b0 /
b0 7
1+
1*
1)
b1 (
b1 .
b1 :
0,
1'
#2
0'
#3
1'
#4
b0 #
b0 1
b0 8
b0 ;
b0 (
b0 .
b0 :
0'
#5
b1111 "
b1111 0
b1111 =
b1111 $
b1111 2
b1111 4
b1111 <
1&
b11111 9
b1 #
b1 1
b1 8
b1 ;
b1 -
b1 /
b1 7
b1 (
b1 .
b1 :
1'
#6
0'
#7
b1110 "
b1110 0
b1110 =
b1110 $
b1110 2
b1110 4
b1110 <
0&
b1110 9
b1111 %
b1111 3
b1111 5
b1111 6
1'
#8
0'
#9
b1 "
b1 0
b1 =
b1 $
b1 2
b1 4
b1 <
b1 9
b1110 %
b1110 3
b1110 5
b1110 6
b10 -
b10 /
b10 7
1'
#10
0'
#11
b1 %
b1 3
b1 5
b1 6
1'
#12
b0 -
b0 /
b0 7
0'
#13
b10 -
b10 /
b10 7
1'
#14
0'
#15
1'
#16
0'
#17
b10 "
b10 0
b10 =
b10 $
b10 2
b10 4
b10 <
b10 9
b11 -
b11 /
b11 7
1'
#18
0'
#19
b11 "
b11 0
b11 =
b11 $
b11 2
b11 4
b11 <
b11 9
b10 %
b10 3
b10 5
b10 6
1'
#20
0'
#21
b1110 "
b1110 0
b1110 =
b1110 $
b1110 2
b1110 4
b1110 <
1&
b11110 9
b11 %
b11 3
b11 5
b11 6
b100 -
b100 /
b100 7
1'
#22
0'
#23
b1111 "
b1111 0
b1111 =
b1111 $
b1111 2
b1111 4
b1111 <
b11111 9
b1110 %
b1110 3
b1110 5
b1110 6
1'
#24
0'
#25
b1110 "
b1110 0
b1110 =
b1110 $
b1110 2
b1110 4
b1110 <
b11110 9
b1111 %
b1111 3
b1111 5
b1111 6
1'
#26
0'
#27
b1111 "
b1111 0
b1111 =
b1111 $
b1111 2
b1111 4
b1111 <
b11111 9
b1110 %
b1110 3
b1110 5
b1110 6
1'
#28
0'
#29
b1110 "
b1110 0
b1110 =
b1110 $
b1110 2
b1110 4
b1110 <
b11110 9
b1111 %
b1111 3
b1111 5
b1111 6
1'
#30
0'
#31
b1111 "
b1111 0
b1111 =
b1111 $
b1111 2
b1111 4
b1111 <
b11111 9
b1110 %
b1110 3
b1110 5
b1110 6
1'
#32
0'
#33
b1110 "
b1110 0
b1110 =
b1110 $
b1110 2
b1110 4
b1110 <
b11110 9
b1111 %
b1111 3
b1111 5
b1111 6
1'
#34
0'
#35
b1111 "
b1111 0
b1111 =
b1111 $
b1111 2
b1111 4
b1111 <
b11111 9
b1110 %
b1110 3
b1110 5
b1110 6
1'
#36
0'
#37
b1110 "
b1110 0
b1110 =
b1110 $
b1110 2
b1110 4
b1110 <
b11110 9
b1111 %
b1111 3
b1111 5
b1111 6
1'
#38
0'
#39
b1111 "
b1111 0
b1111 =
b1111 $
b1111 2
b1111 4
b1111 <
b11111 9
b1110 %
b1110 3
b1110 5
b1110 6
1'
#40
0'
#41
b1110 "
b1110 0
b1110 =
b1110 $
b1110 2
b1110 4
b1110 <
b11110 9
b1111 %
b1111 3
b1111 5
b1111 6
1'
#42
0'
#43
b1111 "
b1111 0
b1111 =
b1111 $
b1111 2
b1111 4
b1111 <
b11111 9
b1110 %
b1110 3
b1110 5
b1110 6
1'
#44
0'
#45
b1110 "
b1110 0
b1110 =
b1110 $
b1110 2
b1110 4
b1110 <
b11110 9
b1111 %
b1111 3
b1111 5
b1111 6
1'
#46
0'
#47
b1111 "
b1111 0
b1111 =
b1111 $
b1111 2
b1111 4
b1111 <
b11111 9
b1110 %
b1110 3
b1110 5
b1110 6
1'
#48
0'
#49
b1110 "
b1110 0
b1110 =
b1110 $
b1110 2
b1110 4
b1110 <
b11110 9
b1111 %
b1111 3
b1111 5
b1111 6
1'
#50
0'
#51
b1111 "
b1111 0
b1111 =
b1111 $
b1111 2
b1111 4
b1111 <
b11111 9
b1110 %
b1110 3
b1110 5
b1110 6
1'
#52
0'
#53
b1110 "
b1110 0
b1110 =
b1110 $
b1110 2
b1110 4
b1110 <
b11110 9
b1111 %
b1111 3
b1111 5
b1111 6
1'
#54
0'
#55
b1111 "
b1111 0
b1111 =
b1111 $
b1111 2
b1111 4
b1111 <
b11111 9
b1110 %
b1110 3
b1110 5
b1110 6
1'
#56
0'
#57
b1110 "
b1110 0
b1110 =
b1110 $
b1110 2
b1110 4
b1110 <
b11110 9
b1111 %
b1111 3
b1111 5
b1111 6
1'
#58
0'
#59
b1111 "
b1111 0
b1111 =
b1111 $
b1111 2
b1111 4
b1111 <
b11111 9
b1110 %
b1110 3
b1110 5
b1110 6
1'
#60
0'
#61
b1110 "
b1110 0
b1110 =
b1110 $
b1110 2
b1110 4
b1110 <
b11110 9
b1111 %
b1111 3
b1111 5
b1111 6
1'
#62
0'
#63
b1111 "
b1111 0
b1111 =
b1111 $
b1111 2
b1111 4
b1111 <
b11111 9
b1110 %
b1110 3
b1110 5
b1110 6
1'
#64
0'
#65
b1110 "
b1110 0
b1110 =
b1110 $
b1110 2
b1110 4
b1110 <
b11110 9
b1111 %
b1111 3
b1111 5
b1111 6
1'
#66
0'
#67
b1111 "
b1111 0
b1111 =
b1111 $
b1111 2
b1111 4
b1111 <
b11111 9
b1110 %
b1110 3
b1110 5
b1110 6
1'
#68
0'
#69
b1110 "
b1110 0
b1110 =
b1110 $
b1110 2
b1110 4
b1110 <
b11110 9
b1111 %
b1111 3
b1111 5
b1111 6
1'
#70
0'
#71
b1111 "
b1111 0
b1111 =
b1111 $
b1111 2
b1111 4
b1111 <
b11111 9
b1110 %
b1110 3
b1110 5
b1110 6
1'
#72
0'
#73
b1110 "
b1110 0
b1110 =
b1110 $
b1110 2
b1110 4
b1110 <
b11110 9
b1111 %
b1111 3
b1111 5
b1111 6
1'
#74
0'
#75
b1111 "
b1111 0
b1111 =
b1111 $
b1111 2
b1111 4
b1111 <
b11111 9
b1110 %
b1110 3
b1110 5
b1110 6
1'
#76
0'
#77
b1110 "
b1110 0
b1110 =
b1110 $
b1110 2
b1110 4
b1110 <
b11110 9
b1111 %
b1111 3
b1111 5
b1111 6
1'
#78
0'
#79
b1111 "
b1111 0
b1111 =
b1111 $
b1111 2
b1111 4
b1111 <
b11111 9
b1110 %
b1110 3
b1110 5
b1110 6
1'
#80
0'
#81
b1110 "
b1110 0
b1110 =
b1110 $
b1110 2
b1110 4
b1110 <
b11110 9
b1111 %
b1111 3
b1111 5
b1111 6
1'
#82
0'
#83
b1111 "
b1111 0
b1111 =
b1111 $
b1111 2
b1111 4
b1111 <
b11111 9
b1110 %
b1110 3
b1110 5
b1110 6
1'
#84
0'
#85
b1110 "
b1110 0
b1110 =
b1110 $
b1110 2
b1110 4
b1110 <
b11110 9
b1111 %
b1111 3
b1111 5
b1111 6
1'
#86
0'
#87
b1111 "
b1111 0
b1111 =
b1111 $
b1111 2
b1111 4
b1111 <
b11111 9
b1110 %
b1110 3
b1110 5
b1110 6
1'
#88
0'
#89
b1110 "
b1110 0
b1110 =
b1110 $
b1110 2
b1110 4
b1110 <
b11110 9
b1111 %
b1111 3
b1111 5
b1111 6
1'
#90
0'
#91
b1111 "
b1111 0
b1111 =
b1111 $
b1111 2
b1111 4
b1111 <
b11111 9
b1110 %
b1110 3
b1110 5
b1110 6
1'
#92
0'
#93
b1110 "
b1110 0
b1110 =
b1110 $
b1110 2
b1110 4
b1110 <
b11110 9
b1111 %
b1111 3
b1111 5
b1111 6
1'
#94
0'
#95
b1111 "
b1111 0
b1111 =
b1111 $
b1111 2
b1111 4
b1111 <
b11111 9
b1110 %
b1110 3
b1110 5
b1110 6
1'
#96
0'
#97
b1110 "
b1110 0
b1110 =
b1110 $
b1110 2
b1110 4
b1110 <
b11110 9
b1111 %
b1111 3
b1111 5
b1111 6
1'
#98
0'
#99
b1111 "
b1111 0
b1111 =
b1111 $
b1111 2
b1111 4
b1111 <
b11111 9
b1110 %
b1110 3
b1110 5
b1110 6
1'
