LAB10/E1/p1.v
//Universidad del Valle de Guatemala
//Gerardo Fuentes
//19389

//Modulo de contador 12 bits
module counter12b(input[11:0] val, input load, en, clk0, reset0,
                  output reg[11:0]sal);

  always@(posedge clk0, load, val, posedge reset0)
    if (reset0) sal <= 12'b0;
    else if (load) sal <= val;
    else if (en) sal <= sal + 1;

endmodule



//Modulo de ROM
module ROM4K(input [11:0]adrs, output [7:0]outt);
  reg[7:0] m [0:4095];

  initial begin
     $readmemb("prueba.g", m);
  end
  assign outt = m[adrs];

endmodule



//Modulo Flipflop tipo D 8 BIT
module F8b(input clk1, reset1, E, input[7:0]outrom4k, output reg[3:0]instr, oprnd);

  always@(posedge clk1, posedge reset1, E)
    if (reset1)  {instr,oprnd}<=8'b0;
    else if (E) {instr,oprnd}<=outrom4k;

endmodule


//Modulo parte 1 procesador
module part1(input clk, reset, ea, eb, ld, input[11:0] val,
             output[3:0]intr, opnd, output[7:0]pbyte, output[11:0]pc);

  counter12b cnt12(val, ld, ea, clk, reset, pc);
  ROM4K       rm4k(pc, pbyte);
  F8b         ft8b(clk, reset, eb, pbyte, intr, opnd);

endmodule

E1/p1_tb.v
//Universidad del Valle de Guatemala
//Gerardo Fuentes
//19389

module testbench();

  reg clk, reset, Ea, Eb, load;
  reg[11:0]VAL;
  wire[3:0]instr, oprnd;
  wire[7:0]prog_byte;
  wire[11:0]PC;

  part1  p1(clk, reset, Ea, Eb, load, VAL, instr, oprnd, prog_byte, PC);

  initial begin
     clk = 0;
     forever #1 clk = ~clk;
  end

  initial begin
    reset = 1;
    #1 reset = 0;
  end

  initial begin
    #1  VAL = 12'b000000000000; Ea=1; Eb=1; load=0;

  end

  initial
    #100 $finish;

  initial begin
    $dumpfile("p1_tb.vcd");
    $dumpvars(0, testbench);
  end

  endmodule

E1/p1_tb.vcd
$date
	Sat Nov 07 11:51:05 2020
$end
$version
	Icarus Verilog
$end
$timescale
	1ps
$end
$scope module testbench $end
$var wire 8 ! prog_byte [7:0] $end
$var wire 4 " oprnd [3:0] $end
$var wire 4 # instr [3:0] $end
$var wire 12 $ PC [11:0] $end
$var reg 1 % Ea $end
$var reg 1 & Eb $end
$var reg 12 ' VAL [11:0] $end
$var reg 1 ( clk $end
$var reg 1 ) load $end
$var reg 1 * reset $end
$scope module p1 $end
$var wire 1 ( clk $end
$var wire 1 % ea $end
$var wire 1 & eb $end
$var wire 1 ) ld $end
$var wire 1 * reset $end
$var wire 12 + val [11:0] $end
$var wire 12 , pc [11:0] $end
$var wire 8 - pbyte [7:0] $end
$var wire 4 . opnd [3:0] $end
$var wire 4 / intr [3:0] $end
$scope module cnt12 $end
$var wire 1 ( clk0 $end
$var wire 1 % en $end
$var wire 1 ) load $end
$var wire 1 * reset0 $end
$var wire 12 0 val [11:0] $end
$var reg 12 1 sal [11:0] $end
$upscope $end
$scope module ft8b $end
$var wire 1 & E $end
$var wire 1 ( clk1 $end
$var wire 1 * reset1 $end
$var wire 8 2 outrom4k [7:0] $end
$var reg 4 3 instr [3:0] $end
$var reg 4 4 oprnd [3:0] $end
$upscope $end
$scope module rm4k $end
$var wire 12 5 adrs [11:0] $end
$var wire 8 6 outt [7:0] $end
$upscope $end
$upscope $end
$upscope $end
$enddefinitions $end
#0
$dumpvars
b1101100 6
b0 5
b0 4
b0 3
b1101100 2
b0 1
bx 0
b0 /
b0 .
b1101100 -
b0 ,
bx +
1*
x)
0(
bx '
x&
x%
b0 $
b0 #
b0 "
b1101100 !
$end
#1
b11001100 !
b11001100 -
b11001100 2
b11001100 6
b1 $
b1 ,
b1 1
b1 5
b110 #
b110 /
b110 3
b1100 "
b1100 .
b1100 4
0)
1&
1%
b0 '
b0 +
b0 0
0*
1(
#2
0(
#3
b11101110 !
b11101110 -
b11101110 2
b11101110 6
b10 $
b10 ,
b10 1
b10 5
b1100 #
b1100 /
b1100 3
1(
#4
0(
#5
b10001000 !
b10001000 -
b10001000 2
b10001000 6
b11 $
b11 ,
b11 1
b11 5
b1110 #
b1110 /
b1110 3
b1110 "
b1110 .
b1110 4
1(
#6
0(
#7
bx !
bx -
bx 2
bx 6
b100 $
b100 ,
b100 1
b100 5
b1000 #
b1000 /
b1000 3
b1000 "
b1000 .
b1000 4
1(
#8
0(
#9
b101 $
b101 ,
b101 1
b101 5
bx #
bx /
bx 3
bx "
bx .
bx 4
1(
#10
0(
#11
b110 $
b110 ,
b110 1
b110 5
1(
#12
0(
#13
b111 $
b111 ,
b111 1
b111 5
1(
#14
0(
#15
b1000 $
b1000 ,
b1000 1
b1000 5
1(
#16
0(
#17
b1001 $
b1001 ,
b1001 1
b1001 5
1(
#18
0(
#19
b1010 $
b1010 ,
b1010 1
b1010 5
1(
#20
0(
#21
b1011 $
b1011 ,
b1011 1
b1011 5
1(
#22
0(
#23
b1100 $
b1100 ,
b1100 1
b1100 5
1(
#24
0(
#25
b1101 $
b1101 ,
b1101 1
b1101 5
1(
#26
0(
#27
b1110 $
b1110 ,
b1110 1
b1110 5
1(
#28
0(
#29
b1111 $
b1111 ,
b1111 1
b1111 5
1(
#30
0(
#31
b10000 $
b10000 ,
b10000 1
b10000 5
1(
#32
0(
#33
b10001 $
b10001 ,
b10001 1
b10001 5
1(
#34
0(
#35
b10010 $
b10010 ,
b10010 1
b10010 5
1(
#36
0(
#37
b10011 $
b10011 ,
b10011 1
b10011 5
1(
#38
0(
#39
b10100 $
b10100 ,
b10100 1
b10100 5
1(
#40
0(
#41
b10101 $
b10101 ,
b10101 1
b10101 5
1(
#42
0(
#43
b10110 $
b10110 ,
b10110 1
b10110 5
1(
#44
0(
#45
b10111 $
b10111 ,
b10111 1
b10111 5
1(
#46
0(
#47
b11000 $
b11000 ,
b11000 1
b11000 5
1(
#48
0(
#49
b11001 $
b11001 ,
b11001 1
b11001 5
1(
#50
0(
#51
b11010 $
b11010 ,
b11010 1
b11010 5
1(
#52
0(
#53
b11011 $
b11011 ,
b11011 1
b11011 5
1(
#54
0(
#55
b11100 $
b11100 ,
b11100 1
b11100 5
1(
#56
0(
#57
b11101 $
b11101 ,
b11101 1
b11101 5
1(
#58
0(
#59
b11110 $
b11110 ,
b11110 1
b11110 5
1(
#60
0(
#61
b11111 $
b11111 ,
b11111 1
b11111 5
1(
#62
0(
#63
b100000 $
b100000 ,
b100000 1
b100000 5
1(
#64
0(
#65
b100001 $
b100001 ,
b100001 1
b100001 5
1(
#66
0(
#67
b100010 $
b100010 ,
b100010 1
b100010 5
1(
#68
0(
#69
b100011 $
b100011 ,
b100011 1
b100011 5
1(
#70
0(
#71
b100100 $
b100100 ,
b100100 1
b100100 5
1(
#72
0(
#73
b100101 $
b100101 ,
b100101 1
b100101 5
1(
#74
0(
#75
b100110 $
b100110 ,
b100110 1
b100110 5
1(
#76
0(
#77
b100111 $
b100111 ,
b100111 1
b100111 5
1(
#78
0(
#79
b101000 $
b101000 ,
b101000 1
b101000 5
1(
#80
0(
#81
b101001 $
b101001 ,
b101001 1
b101001 5
1(
#82
0(
#83
b101010 $
b101010 ,
b101010 1
b101010 5
1(
#84
0(
#85
b101011 $
b101011 ,
b101011 1
b101011 5
1(
#86
0(
#87
b101100 $
b101100 ,
b101100 1
b101100 5
1(
#88
0(
#89
b101101 $
b101101 ,
b101101 1
b101101 5
1(
#90
0(
#91
b101110 $
b101110 ,
b101110 1
b101110 5
1(
#92
0(
#93
b101111 $
b101111 ,
b101111 1
b101111 5
1(
#94
0(
#95
b110000 $
b110000 ,
b110000 1
b110000 5
1(
#96
0(
#97
b110001 $
b110001 ,
b110001 1
b110001 5
1(
#98
0(
#99
b110010 $
b110010 ,
b110010 1
b110010 5
1(
